bdd2dfa/__init__.py
bdd2dfa/b2d.py
bdd2dfa-1.0.10.dist-info/LICENSE
bdd2dfa-1.0.10.dist-info/WHEEL
bdd2dfa-1.0.10.dist-info/METADATA
bdd2dfa-1.0.10.dist-info/RECORD
