Metadata-Version: 2.1
Name: bdd2dfa
Version: 1.0.10
Summary: Python library for converting binary decision diagrams to automata.
Home-page: https://github.com/mvcisback/bdd2dfa
License: MIT
Author: Marcell Vazquez-Chanlatte
Author-email: mvc@linux.com
Requires-Python: >=3.9,<4.0
Classifier: License :: OSI Approved :: MIT License
Classifier: Programming Language :: Python :: 3
Classifier: Programming Language :: Python :: 3.10
Classifier: Programming Language :: Python :: 3.9
Requires-Dist: attrs (>=22.0.0,<23.0.0)
Requires-Dist: dfa (>=4.0.0,<5.0.0)
Project-URL: Repository, https://github.com/mvcisback/bdd2dfa
